{"cameraMode":{"drawMode":0,"name":"Shaded","section":"Shading Mode"},"sceneLighting":true,"audioPlay":false,"sceneViewState":{"m_AlwaysRefresh":false,"showFog":true,"showSkybox":true,"showFlares":true,"showImageEffects":true,"showParticleSystems":true,"showVisualEffectGraphs":true,"m_FxEnabled":true},"in2DMode":false,"pivot":{"x":5.909515380859375,"y":9.465723991394043,"z":-3.116875648498535},"rotation":{"x":0.014101504348218441,"y":0.026379207149147989,"z":0.00042618319275788963,"w":-0.999567985534668},"size":10.704244613647461,"orthographic":false}